zhy_mcp_demo/__init__.py
zhy_mcp_demo-0.1.0.dist-info/WHEEL
zhy_mcp_demo-0.1.0.dist-info/entry_points.txt
zhy_mcp_demo-0.1.0.dist-info/METADATA
zhy_mcp_demo-0.1.0.dist-info/RECORD
